NStudyPy/PyDate.py
NStudyPy/PyEnv.py
NStudyPy/PyFile.py
NStudyPy/PyLogger.py
NStudyPy/PyRe.py
NStudyPy/PyString.py
NStudyPy/PyTools.py
NStudyPy/PyWeb.py
NStudyPy/__init__.py
NStudyPy/py.typed
nstudypy-0.0.20.dist-info/METADATA
nstudypy-0.0.20.dist-info/WHEEL
nstudypy-0.0.20.dist-info/licenses/LICENSE
nstudypy-0.0.20.dist-info/RECORD
