Metadata-Version: 2.4
Name: NStudyPy
Version: 0.0.20
Summary: A NStudyPy useful tools
Project-URL: Homepage, https://nstudy.org
Project-URL: Documentation, https://hub.nstudy.org
Project-URL: Bug Tracker, https://github.com/lizhq/NStudyPy/issues
Author-email: Jack Li <lizhq08@gmail.com>
Maintainer: Jack Li contributors
License: MIT License
License-File: LICENSE
Keywords: NStudyPy,tools
Classifier: Development Status :: 4 - Beta
Classifier: Intended Audience :: Developers
Classifier: License :: OSI Approved :: MIT License
Classifier: Operating System :: OS Independent
Classifier: Programming Language :: Python :: 3
Classifier: Programming Language :: Python :: 3.10
Classifier: Topic :: Software Development :: Libraries :: Python Modules
Requires-Python: >=3.10
Requires-Dist: requests>=2.32.5
